pybigquery/__init__.py
pybigquery/_helpers.py
pybigquery/api.py
pybigquery/parse_url.py
pybigquery/requirements.py
pybigquery/sqlalchemy_bigquery.py
pybigquery-0.10.2.dist-info/AUTHORS
pybigquery-0.10.2.dist-info/LICENSE
pybigquery-0.10.2.dist-info/METADATA
pybigquery-0.10.2.dist-info/WHEEL
pybigquery-0.10.2.dist-info/entry_points.txt
pybigquery-0.10.2.dist-info/top_level.txt
pybigquery-0.10.2.dist-info/RECORD
