Metadata-Version: 2.1
Name: pybigquery
Version: 0.10.2
Summary: OBSOLETE SQLAlchemy dialect for BigQuery
Home-page: https://github.com/googleapis/python-bigquery-sqlalchemy
Author: The PyBigQuery Authors
Author-email: googleapis-packages@google.com
License: UNKNOWN
Keywords: bigquery,sqlalchemy
Platform: Posix; MacOS X; Windows
Classifier: Development Status :: 7 - Inactive
Classifier: Intended Audience :: Developers
Classifier: License :: OSI Approved :: MIT License
Classifier: Programming Language :: Python
Classifier: Programming Language :: Python :: 3
Classifier: Programming Language :: Python :: 3.6
Classifier: Programming Language :: Python :: 3.7
Classifier: Programming Language :: Python :: 3.8
Classifier: Programming Language :: Python :: 3.9
Classifier: Operating System :: OS Independent
Classifier: Topic :: Database :: Front-Ends
Requires-Python: >=3.6, <3.10
